MANIFEST.in
setup.cfg
setup.py
versioneer.py
skymap/__init__.py
skymap/_version.py
skymap/constants.py
skymap/core.py
skymap/healpix.py
skymap/survey.py
skymap/utils.py
skymap.egg-info/PKG-INFO
skymap.egg-info/SOURCES.txt
skymap.egg-info/dependency_links.txt
skymap.egg-info/requires.txt
skymap.egg-info/top_level.txt
skymap/data/bliss-poly.txt
skymap/data/ccd_corners_xy_fill.dat
skymap/data/decals-poly.txt
skymap/data/derosita-poly.txt
skymap/data/des-round13-poly.txt
skymap/data/des-round17-poly.txt
skymap/data/macho_corners_xy.dat
skymap/data/maglites-poly.txt
skymap/data/smash_fields_final.txt
skymap/instrument/__init__.py
skymap/instrument/camera.py
skymap/instrument/decam.py
skymap/instrument/macho.py