Metadata-Version: 1.1
Name: skymap
Version: 0.2.0
Summary: Python tools for making skymaps
Home-page: https://github.com/kadrlica/skymap
Author: Alex Drlica-Wagner
Author-email: kadrlica@fnal.gov
License: UNKNOWN
Keywords: python astronomy plotting
Platform: any
Classifier: Programming Language :: Python
Classifier: Development Status :: 2 - Pre-Alpha
Classifier: Natural Language :: English
Classifier: Intended Audience :: Science/Research
